{
	"info": {
		"_postman_id": "ea0e18ff-61d8-4ca4-8359-6ee2cdd24afb",
		"name": "api calls",
		"schema": "https://schema.getpostman.com/json/collection/v2.1.0/collection.json",
		"_uid": "15419153-ea0e18ff-61d8-4ca4-8359-6ee2cdd24afb"
	},
	"item": [
		{
			"name": "good will",
			"id": "4929af86-8052-4bd0-a29c-582c03b707a2",
			"protocolProfileBehavior": {
				"disableBodyPruning": true
			},
			"request": {
				"method": "GET",
				"header": [],
				"url": {
					"raw": "good will",
					"host": [
						"good will"
					]
				}
			},
			"response": []
		}
	]
}